<DOMSymbolItem xmlns:xsi="http://www.w3.org/2001/XMLSchema-instance" xmlns="http://ns.adobe.com/xfl/2008/" name="Symbol 17" itemID="5a81980f-00000d8f" lastModified="1518442511">
  <timeline>
    <DOMTimeline name="Symbol 17">
      <layers>
        <DOMLayer name="Layer_1" color="#00FFFF" current="true" isSelected="true">
          <frames>
            <DOMFrame index="0" keyMode="9728">
              <elements>
                <DOMSymbolInstance libraryItemName="FlashAICB/Layer 7/&amp;#060Path&amp;#062" selected="true" blendMode="layer" centerPoint3DX="18.6" centerPoint3DY="22.2">
                  <matrix>
                    <Matrix tx="0.05"/>
                  </matrix>
                  <transformationPoint>
                    <Point x="18.55" y="22.2"/>
                  </transformationPoint>
                  <color>
                    <Color alphaMultiplier="0.80078125"/>
                  </color>
                </DOMSymbolInstance>
              </elements>
            </DOMFrame>
          </frames>
        </DOMLayer>
      </layers>
    </DOMTimeline>
  </timeline>
</DOMSymbolItem>